ansible2puml/__init_.py
ansible2puml/__main__.py
ansible2puml/cli.py
ansible2puml/functions.py
ansible2puml-0.3.1.dist-info/LICENSE
ansible2puml-0.3.1.dist-info/METADATA
ansible2puml-0.3.1.dist-info/WHEEL
ansible2puml-0.3.1.dist-info/entry_points.txt
ansible2puml-0.3.1.dist-info/top_level.txt
ansible2puml-0.3.1.dist-info/RECORD
