Metadata-Version: 2.1
Name: ansible2puml
Version: 0.3.1
Summary: Create an PlantUML Activity Diagram from Playbooks or Roles trough Python.
Home-page: https://github.com/ProfileID/ansible2puml
Author: profileid
Author-email: profileid@protonmail.com
License: MIT
Platform: UNKNOWN
Classifier: Programming Language :: Python :: 3.6
Classifier: Programming Language :: Python :: 3.7
Classifier: Programming Language :: Python :: 3.8
Requires-Dist: click
Requires-Dist: pyyaml
Requires-Dist: jinja2
Requires-Dist: plantuml
Requires-Dist: six
